scry_blast/__init__.py
scry_blast/config.py
scry_blast/fetch_sequence.py
scry_blast/options.py
scry_blast/run_blast.py
scry_blast-0.6.dist-info/DESCRIPTION.rst
scry_blast-0.6.dist-info/METADATA
scry_blast-0.6.dist-info/RECORD
scry_blast-0.6.dist-info/WHEEL
scry_blast-0.6.dist-info/metadata.json
scry_blast-0.6.dist-info/top_level.txt
