Metadata-Version: 2.0
Name: scry-blast
Version: 0.6
Summary: A SCRY service to extend SPARQL with procedures that run NCBI's BLAST program
Home-page: http://www.few.vu.nl/
Author: Bas Stringer
Author-email: b.stringer@vu.nl
License: MIT
Keywords: scry sparql math service extension ncbi blast bioinformatics
Platform: UNKNOWN
Classifier: Development Status :: 4 - Beta
Classifier: Intended Audience :: Developers
Classifier: Intended Audience :: Healthcare Industry
Classifier: Intended Audience :: Information Technology
Classifier: Intended Audience :: Science/Research
Classifier: License :: OSI Approved :: MIT License
Classifier: Operating System :: OS Independent
Classifier: Programming Language :: Python
Classifier: Programming Language :: Python :: 2.7
Classifier: Topic :: Scientific/Engineering :: Bio-Informatics
Requires-Dist: scry (>=0.1)
